pcprox_reader/__init__.py
pcprox_reader/cardreader.py
pcprox_reader/cli.py
pcprox_reader/udev_rule.py
pcprox_reader-0.4.0.dist-info/AUTHORS.rst
pcprox_reader-0.4.0.dist-info/LICENSE
pcprox_reader-0.4.0.dist-info/METADATA
pcprox_reader-0.4.0.dist-info/WHEEL
pcprox_reader-0.4.0.dist-info/entry_points.txt
pcprox_reader-0.4.0.dist-info/top_level.txt
pcprox_reader-0.4.0.dist-info/RECORD
