Metadata-Version: 2.1
Name: pcprox-reader
Version: 0.4.0
Summary: Library for reading cards via usb RFIDeas pc prox readers
Home-page: https://github.com/kellerjustin/pcprox_reader
Author: Justin Keller
Author-email: kellerjustin@protonmail.com
License: MIT license
Keywords: pcprox_reader
Platform: UNKNOWN
Classifier: Development Status :: 2 - Pre-Alpha
Classifier: Intended Audience :: Developers
Classifier: License :: OSI Approved :: MIT License
Classifier: Natural Language :: English
Classifier: Programming Language :: Python :: 2
Classifier: Programming Language :: Python :: 2.7
Classifier: Programming Language :: Python :: 3
Classifier: Programming Language :: Python :: 3.4
Classifier: Programming Language :: Python :: 3.5
Classifier: Programming Language :: Python :: 3.6
Classifier: Programming Language :: Python :: 3.7
Requires-Dist: Click (>=6.0)
Requires-Dist: pyusb
